{
  "units": [
    {
      "unitName": "Infantry",
      "healthPoints": 6,
      "movementSpeed": 2,
      "attack": 2,
      "defense": 3,
      "recruitmentTime": 10,
      "resources": [
        { "resourceName": "Construction Materials", "quantity": 1 },
        { "resourceName": "Steel", "quantity": 1 }
      ]
    },
    {
      "unitName": "Engineer",
      "healthPoints": 4,
      "movementSpeed": 1.5,
      "attack": 5,
      "defense": 1.5,
      "recruitmentTime": 2,
      "resources": [
        { "resourceName": "Construction Materials", "quantity": 1 },
        { "resourceName": "Steel", "quantity": 1 }
      ]
    },
    {
      "unitName": "Sniper",
      "healthPoints": 2.5,
      "movementSpeed": 2.5,
      "attack": 4,
      "defense": 0.5,
      "recruitmentTime": 5,
      "resources": [
        { "resourceName": "Construction Materials", "quantity": 1 },
        { "resourceName": "Steel", "quantity": 1 }
      ]
    },
    {
      "unitName": "Armored Personnel Carrier",
      "healthPoints": 40,
      "movementSpeed": 15,
      "attack": 15,
      "defense": 12,
      "recruitmentTime": 20,
      "resources": [
        { "resourceName": "Construction Materials", "quantity": 1 },
        { "resourceName": "Steel", "quantity": 1 }
      ]
    },
    {
      "unitName": "Main Battle Tank",
      "healthPoints": 80,
      "movementSpeed": 10,
      "attack": 40,
      "defense": 40,
      "recruitmentTime": 20,
      "resources": [
        { "resourceName": "Construction Materials", "quantity": 1 },
        { "resourceName": "Steel", "quantity": 1 }
      ]
    },
    {
      "unitName": "Artillery",
      "healthPoints": 20,
      "movementSpeed": 7.5,
      "attack": 100,
      "defense": 10,
      "recruitmentTime": 20,
      "resources": [
        { "resourceName": "Construction Materials", "quantity": 1 },
        { "resourceName": "Steel", "quantity": 1 }
      ]
    },
    {
      "unitName": "Jet Fighter",
      "healthPoints": 60,
      "movementSpeed": 50,
      "attack": 40,
      "defense": 18,
      "recruitmentTime": 20,
      "resources": [
        { "resourceName": "Construction Materials", "quantity": 1 },
        { "resourceName": "Steel", "quantity": 1 }
      ]
    },
    {
      "unitName": "Bomber",
      "healthPoints": 40,
      "movementSpeed": 30,
      "attack": 150,
      "defense": 15,
      "recruitmentTime": 20,
      "resources": [
        { "resourceName": "Construction Materials", "quantity": 1 },
        { "resourceName": "Steel", "quantity": 1 }
      ]
    },
    {
      "unitName": "Recon",
      "healthPoints": 20,
      "movementSpeed": 20,
      "attack": 2,
      "defense": 0,
      "recruitmentTime": 20,
      "resources": [
        { "resourceName": "Construction Materials", "quantity": 1 },
        { "resourceName": "Steel", "quantity": 1 }
      ]
    }
  ]
}
